topsispy/__init__.py
topsispy/topsis.py
topsispy-0.0.1.dist-info/LICENSE.txt
topsispy-0.0.1.dist-info/METADATA
topsispy-0.0.1.dist-info/WHEEL
topsispy-0.0.1.dist-info/top_level.txt
topsispy-0.0.1.dist-info/RECORD
