Metadata-Version: 2.1
Name: topsispy
Version: 0.0.1
Summary: This is a Python Package implementing Topsis used for multi-criteria decision analysis method
Home-page: https://github.com/shivambehl/TopsisPy
Author: Shivam Behl
Author-email: shivambehl123@gmail.com
License: MIT
Keywords: topsis,mcda,UCS633,TIET
Platform: UNKNOWN
Classifier: Development Status :: 3 - Alpha
Classifier: Intended Audience :: Developers
Classifier: Topic :: Software Development :: Build Tools
Classifier: License :: OSI Approved :: MIT License
Requires-Dist: numpy
